piaso/__init__.py
piaso/plotting/__init__.py
piaso/plotting/_plotByCluster.py
piaso/plotting/_plotCellMetaInfo.py
piaso/plotting/_plotEmbedding.py
piaso/plotting/_plotLigandReceptor.py
piaso/plotting/_plotLigandReceptorLollipop.py
piaso/plotting/color.py
piaso/preprocessing/__init__.py
piaso/preprocessing/_dataFrame_processing.py
piaso/preprocessing/_spatialPreprocessing.py
piaso/tools/__init__.py
piaso/tools/_clustering.py
piaso/tools/_integration.py
piaso/tools/_ligandReceptor.py
piaso/tools/_markerdb.py
piaso/tools/_normalization.py
piaso/tools/_predictCellType.py
piaso/tools/_runGDR.py
piaso/tools/_runSVD.py
piaso_tools-1.0.3.dist-info/METADATA
piaso_tools-1.0.3.dist-info/WHEEL
piaso_tools-1.0.3.dist-info/licenses/LICENSE
piaso_tools-1.0.3.dist-info/RECORD
